djangorestframework_serializer_query_optimizations-0.1.0.dist-info/DESCRIPTION.rst
djangorestframework_serializer_query_optimizations-0.1.0.dist-info/METADATA
djangorestframework_serializer_query_optimizations-0.1.0.dist-info/RECORD
djangorestframework_serializer_query_optimizations-0.1.0.dist-info/WHEEL
djangorestframework_serializer_query_optimizations-0.1.0.dist-info/metadata.json
djangorestframework_serializer_query_optimizations-0.1.0.dist-info/top_level.txt
drf_serializer_query_optimizations/__init__.py
drf_serializer_query_optimizations/serializers.py
drf_serializer_query_optimizations/__pycache__/__init__.cpython-35.pyc
drf_serializer_query_optimizations/__pycache__/serializers.cpython-35.pyc
