Metadata-Version: 2.0
Name: djangorestframework-serializer-query-optimizations
Version: 0.1.0
Summary: Adds the possibility to do `select_related()` and `prefetch_related()` queries on querysets provided to Django REST Framework (DRF) model serializers.
Home-page: https://gitlab.com/gorgonzola/djangorestframework-serializer-query-optimizations
Author: Mikkel Munch Mortensen
Author-email: 3xm@detfalskested.dk
License: MIT
Platform: UNKNOWN
Classifier: Development Status :: 2 - Pre-Alpha
Classifier: Environment :: Web Environment
Classifier: Framework :: Django
Classifier: Intended Audience :: Developers
Classifier: License :: OSI Approved :: MIT License
Classifier: Operating System :: OS Independent
Classifier: Natural Language :: English
Classifier: Programming Language :: Python :: 2
Classifier: Programming Language :: Python :: 3
Classifier: Topic :: Internet :: WWW/HTTP
